{
  "versions": [
    {
      "git-tree": "30c7fc023e0d65c371ccae3d7aeccd337aeebe73",
      "version": "5.0.14.93333.0",
      "port-version": 5
    },
    {
      "git-tree": "642f4cd76e9d9c7d50b63839acd305d211f5e076",
      "version": "5.0.14.93333.0",
      "port-version": 4
    },
    {
      "git-tree": "8c769db52ebc104e5d8711655aecbfe95fee1b1b",
      "version": "5.0.14.93333.0",
      "port-version": 3
    },
    {
      "git-tree": "ded9c1dc5db05de6f7a8785ca7baf6321aa02a99",
      "version": "5.0.14.93333.0",
      "port-version": 2
    },
    {
      "git-tree": "64c667ece76c2e3178c780733366e25cce21562c",
      "version": "5.0.14.93333.0",
      "port-version": 0
    },
    {
      "git-tree": "66ff8c72142d474029603d0dcc700545d3fad048",
      "version": "5.0.14.93333.0",
      "port-version": 1
    }
  ]
}
